MANIFEST.in
README.md
setup.cfg
setup.py
ampd/__init__.py
ampd/client.py
ampd/errors.py
ampd/glib.py
ampd/request.py
ampd.egg-info/PKG-INFO
ampd.egg-info/SOURCES.txt
ampd.egg-info/dependency_links.txt
ampd.egg-info/requires.txt
ampd.egg-info/top_level.txt
examples/ampc
examples/ampc-gtk