Metadata-Version: 2.1
Name: ampd
Version: 0.2.12
Summary: Asynchronous MPD client library
Home-page: https://github.com/begnac/ampd
Author: Itaï BEN YAACOV
Author-email: candeb@free.fr
License: GPLv3+
Keywords: mpd,client,asynchronous
Platform: UNKNOWN
Classifier: Development Status :: 5 - Production/Stable
Classifier: Intended Audience :: Developers
Classifier: License :: OSI Approved :: GNU General Public License v3 or later (GPLv3+)
Classifier: Operating System :: POSIX :: Linux
Classifier: Programming Language :: Python :: 3
Classifier: Programming Language :: Python :: 3.9
Classifier: Topic :: Multimedia :: Sound/Audio
Classifier: Topic :: Software Development :: Libraries :: Python Modules
